{
	"info": {
		"_postman_id": "409de23b-efc4-408b-819d-d855ed28448d",
		"name": "RESTful API with Kotlin 1.6.10 and Spring Boot 3.0.0-M1",
		"description": "Some description about your API.",
		"schema": "https://schema.getpostman.com/json/collection/v2.1.0/collection.json"
	},
	"item": [
		{
			"name": "api",
			"item": [
				{
					"name": "person/v1",
					"item": [
						{
							"name": "Finds all People",
							"request": {
								"method": "GET",
								"header": [
									{
										"key": "Accept",
										"value": "application/json"
									},
									{
										"key": "Authorization",
										"value": "Bearer {{refreshToken}}",
										"type": "text"
									}
								],
								"url": {
									"raw": "{{baseUrl}}/api/person/v1?page=0&limit=12&direction=asc",
									"host": [
										"{{baseUrl}}"
									],
									"path": [
										"api",
										"person",
										"v1"
									],
									"query": [
										{
											"key": "page",
											"value": "0"
										},
										{
											"key": "limit",
											"value": "12"
										},
										{
											"key": "direction",
											"value": "asc"
										}
									]
								},
								"description": "Finds all People."
							},
							"response": [
								{
									"name": "Success",
									"originalRequest": {
										"method": "GET",
										"header": [],
										"url": {
											"raw": "{{baseUrl}}/api/person/v1?page=0&limit=12&direction=asc",
											"host": [
												"{{baseUrl}}"
											],
											"path": [
												"api",
												"person",
												"v1"
											],
											"query": [
												{
													"key": "page",
													"value": "0"
												},
												{
													"key": "limit",
													"value": "12"
												},
												{
													"key": "direction",
													"value": "asc"
												}
											]
										}
									},
									"status": "OK",
									"code": 200,
									"_postman_previewlanguage": "json",
									"header": [
										{
											"key": "Content-Type",
											"value": "application/json"
										}
									],
									"cookie": [],
									"body": "[\n  {\n    \"id\": 58572628,\n    \"firstName\": \"aliquip laboris ex\",\n    \"lastName\": \"do dolore in in\",\n    \"gender\": \"adipisicing aliqua\",\n    \"address\": \"Duis laborum aliquip quis\",\n    \"enabled\": false,\n    \"_links\": {\n      \"eu_97\": {\n        \"href\": \"enim exercitat\",\n        \"hreflang\": \"sit\",\n        \"title\": \"quis pariatur irure dolore\",\n        \"type\": \"in labore consectetur\",\n        \"deprecation\": \"sunt\",\n        \"profile\": \"pariatur anim nisi amet non\",\n        \"name\": \"proident\",\n        \"templated\": true\n      },\n      \"non_7f\": {\n        \"href\": \"reprehenderit proident in ex\",\n        \"hreflang\": \"voluptate ea Excepteur\",\n        \"title\": \"amet pariatur eiusmod\",\n        \"type\": \"cupidatat aliqua dolor deserunt pariatur\",\n        \"deprecation\": \"e\",\n        \"profile\": \"laborum eiusmod id ex\",\n        \"name\": \"Ut culpa fugia\",\n        \"templated\": false\n      }\n    }\n  },\n  {\n    \"id\": 25630671,\n    \"firstName\": \"non ut velit Lorem dolor\",\n    \"lastName\": \"qui id\",\n    \"gender\": \"Duis consequat proident\",\n    \"address\": \"id non laboris anim\",\n    \"enabled\": true,\n    \"_links\": {\n      \"nisib\": {\n        \"href\": \"Ut in eu dolore et\",\n        \"hreflang\": \"sunt sed\",\n        \"title\": \"tempor\",\n        \"type\": \"et aliquip deserunt\",\n        \"deprecation\": \"dolore consequat nulla officia\",\n        \"profile\": \"proident deserunt elit\",\n        \"name\": \"ea nostrud officia laboris\",\n        \"templated\": false\n      },\n      \"consequat_ac\": {\n        \"href\": \"officia\",\n        \"hreflang\": \"do amet est pariatur\",\n        \"title\": \"ea\",\n        \"type\": \"nisi anim voluptate\",\n        \"deprecation\": \"Excepteur\",\n        \"profile\": \"consectetur ipsum incididunt dolor\",\n        \"name\": \"mollit reprehenderi\",\n        \"templated\": true\n      }\n    }\n  }\n]"
								},
								{
									"name": "No Content",
									"originalRequest": {
										"method": "GET",
										"header": [],
										"url": {
											"raw": "{{baseUrl}}/api/person/v1?page=0&limit=12&direction=asc",
											"host": [
												"{{baseUrl}}"
											],
											"path": [
												"api",
												"person",
												"v1"
											],
											"query": [
												{
													"key": "page",
													"value": "0"
												},
												{
													"key": "limit",
													"value": "12"
												},
												{
													"key": "direction",
													"value": "asc"
												}
											]
										}
									},
									"status": "No Content",
									"code": 204,
									"_postman_previewlanguage": "json",
									"header": [
										{
											"key": "Content-Type",
											"value": "application/json"
										}
									],
									"cookie": [],
									"body": "{}"
								},
								{
									"name": "Bad Request",
									"originalRequest": {
										"method": "GET",
										"header": [],
										"url": {
											"raw": "{{baseUrl}}/api/person/v1?page=0&limit=12&direction=asc",
											"host": [
												"{{baseUrl}}"
											],
											"path": [
												"api",
												"person",
												"v1"
											],
											"query": [
												{
													"key": "page",
													"value": "0"
												},
												{
													"key": "limit",
													"value": "12"
												},
												{
													"key": "direction",
													"value": "asc"
												}
											]
										}
									},
									"status": "Bad Request",
									"code": 400,
									"_postman_previewlanguage": "json",
									"header": [
										{
											"key": "Content-Type",
											"value": "application/json"
										}
									],
									"cookie": [],
									"body": "{}"
								},
								{
									"name": "Unauthorized",
									"originalRequest": {
										"method": "GET",
										"header": [],
										"url": {
											"raw": "{{baseUrl}}/api/person/v1?page=0&limit=12&direction=asc",
											"host": [
												"{{baseUrl}}"
											],
											"path": [
												"api",
												"person",
												"v1"
											],
											"query": [
												{
													"key": "page",
													"value": "0"
												},
												{
													"key": "limit",
													"value": "12"
												},
												{
													"key": "direction",
													"value": "asc"
												}
											]
										}
									},
									"status": "Unauthorized",
									"code": 401,
									"_postman_previewlanguage": "json",
									"header": [
										{
											"key": "Content-Type",
											"value": "application/json"
										}
									],
									"cookie": [],
									"body": "{}"
								},
								{
									"name": "Not Found",
									"originalRequest": {
										"method": "GET",
										"header": [],
										"url": {
											"raw": "{{baseUrl}}/api/person/v1?page=0&limit=12&direction=asc",
											"host": [
												"{{baseUrl}}"
											],
											"path": [
												"api",
												"person",
												"v1"
											],
											"query": [
												{
													"key": "page",
													"value": "0"
												},
												{
													"key": "limit",
													"value": "12"
												},
												{
													"key": "direction",
													"value": "asc"
												}
											]
										}
									},
									"status": "Not Found",
									"code": 404,
									"_postman_previewlanguage": "json",
									"header": [
										{
											"key": "Content-Type",
											"value": "application/json"
										}
									],
									"cookie": [],
									"body": "{}"
								},
								{
									"name": "Internal error",
									"originalRequest": {
										"method": "GET",
										"header": [],
										"url": {
											"raw": "{{baseUrl}}/api/person/v1?page=0&limit=12&direction=asc",
											"host": [
												"{{baseUrl}}"
											],
											"path": [
												"api",
												"person",
												"v1"
											],
											"query": [
												{
													"key": "page",
													"value": "0"
												},
												{
													"key": "limit",
													"value": "12"
												},
												{
													"key": "direction",
													"value": "asc"
												}
											]
										}
									},
									"status": "Internal Server Error",
									"code": 500,
									"_postman_previewlanguage": "json",
									"header": [
										{
											"key": "Content-Type",
											"value": "application/json"
										}
									],
									"cookie": [],
									"body": "{}"
								}
							]
						},
						{
							"name": "Find persons by name",
							"request": {
								"method": "GET",
								"header": [
									{
										"key": "Accept",
										"value": "application/json"
									},
									{
										"key": "Authorization",
										"value": "Bearer {{refreshToken}}",
										"type": "text"
									}
								],
								"url": {
									"raw": "{{baseUrl}}/api/person/v1/findPersonByName/:firstName?page=0&limit=12&direction=asc",
									"host": [
										"{{baseUrl}}"
									],
									"path": [
										"api",
										"person",
										"v1",
										"findPersonByName",
										":firstName"
									],
									"query": [
										{
											"key": "page",
											"value": "0"
										},
										{
											"key": "limit",
											"value": "12"
										},
										{
											"key": "direction",
											"value": "asc"
										}
									],
									"variable": [
										{
											"key": "firstName",
											"value": "id",
											"description": "(Required) "
										}
									]
								},
								"description": "Find persons by name"
							},
							"response": [
								{
									"name": "Success",
									"originalRequest": {
										"method": "GET",
										"header": [],
										"url": {
											"raw": "{{baseUrl}}/api/person/v1/findPersonByName/:firstName?page=0&limit=12&direction=asc",
											"host": [
												"{{baseUrl}}"
											],
											"path": [
												"api",
												"person",
												"v1",
												"findPersonByName",
												":firstName"
											],
											"query": [
												{
													"key": "page",
													"value": "0"
												},
												{
													"key": "limit",
													"value": "12"
												},
												{
													"key": "direction",
													"value": "asc"
												}
											],
											"variable": [
												{
													"key": "firstName",
													"value": "id",
													"description": "(Required) "
												}
											]
										}
									},
									"status": "OK",
									"code": 200,
									"_postman_previewlanguage": "json",
									"header": [
										{
											"key": "Content-Type",
											"value": "application/json"
										}
									],
									"cookie": [],
									"body": "[\n  {\n    \"id\": 58572628,\n    \"firstName\": \"aliquip laboris ex\",\n    \"lastName\": \"do dolore in in\",\n    \"gender\": \"adipisicing aliqua\",\n    \"address\": \"Duis laborum aliquip quis\",\n    \"enabled\": false,\n    \"_links\": {\n      \"eu_97\": {\n        \"href\": \"enim exercitat\",\n        \"hreflang\": \"sit\",\n        \"title\": \"quis pariatur irure dolore\",\n        \"type\": \"in labore consectetur\",\n        \"deprecation\": \"sunt\",\n        \"profile\": \"pariatur anim nisi amet non\",\n        \"name\": \"proident\",\n        \"templated\": true\n      },\n      \"non_7f\": {\n        \"href\": \"reprehenderit proident in ex\",\n        \"hreflang\": \"voluptate ea Excepteur\",\n        \"title\": \"amet pariatur eiusmod\",\n        \"type\": \"cupidatat aliqua dolor deserunt pariatur\",\n        \"deprecation\": \"e\",\n        \"profile\": \"laborum eiusmod id ex\",\n        \"name\": \"Ut culpa fugia\",\n        \"templated\": false\n      }\n    }\n  },\n  {\n    \"id\": 25630671,\n    \"firstName\": \"non ut velit Lorem dolor\",\n    \"lastName\": \"qui id\",\n    \"gender\": \"Duis consequat proident\",\n    \"address\": \"id non laboris anim\",\n    \"enabled\": true,\n    \"_links\": {\n      \"nisib\": {\n        \"href\": \"Ut in eu dolore et\",\n        \"hreflang\": \"sunt sed\",\n        \"title\": \"tempor\",\n        \"type\": \"et aliquip deserunt\",\n        \"deprecation\": \"dolore consequat nulla officia\",\n        \"profile\": \"proident deserunt elit\",\n        \"name\": \"ea nostrud officia laboris\",\n        \"templated\": false\n      },\n      \"consequat_ac\": {\n        \"href\": \"officia\",\n        \"hreflang\": \"do amet est pariatur\",\n        \"title\": \"ea\",\n        \"type\": \"nisi anim voluptate\",\n        \"deprecation\": \"Excepteur\",\n        \"profile\": \"consectetur ipsum incididunt dolor\",\n        \"name\": \"mollit reprehenderi\",\n        \"templated\": true\n      }\n    }\n  }\n]"
								},
								{
									"name": "No Content",
									"originalRequest": {
										"method": "GET",
										"header": [],
										"url": {
											"raw": "{{baseUrl}}/api/person/v1/findPersonByName/:firstName?page=0&limit=12&direction=asc",
											"host": [
												"{{baseUrl}}"
											],
											"path": [
												"api",
												"person",
												"v1",
												"findPersonByName",
												":firstName"
											],
											"query": [
												{
													"key": "page",
													"value": "0"
												},
												{
													"key": "limit",
													"value": "12"
												},
												{
													"key": "direction",
													"value": "asc"
												}
											],
											"variable": [
												{
													"key": "firstName",
													"value": "id",
													"description": "(Required) "
												}
											]
										}
									},
									"status": "No Content",
									"code": 204,
									"_postman_previewlanguage": "json",
									"header": [
										{
											"key": "Content-Type",
											"value": "application/json"
										}
									],
									"cookie": [],
									"body": "{}"
								},
								{
									"name": "Bad Request",
									"originalRequest": {
										"method": "GET",
										"header": [],
										"url": {
											"raw": "{{baseUrl}}/api/person/v1/findPersonByName/:firstName?page=0&limit=12&direction=asc",
											"host": [
												"{{baseUrl}}"
											],
											"path": [
												"api",
												"person",
												"v1",
												"findPersonByName",
												":firstName"
											],
											"query": [
												{
													"key": "page",
													"value": "0"
												},
												{
													"key": "limit",
													"value": "12"
												},
												{
													"key": "direction",
													"value": "asc"
												}
											],
											"variable": [
												{
													"key": "firstName",
													"value": "id",
													"description": "(Required) "
												}
											]
										}
									},
									"status": "Bad Request",
									"code": 400,
									"_postman_previewlanguage": "json",
									"header": [
										{
											"key": "Content-Type",
											"value": "application/json"
										}
									],
									"cookie": [],
									"body": "{}"
								},
								{
									"name": "Unauthorized",
									"originalRequest": {
										"method": "GET",
										"header": [],
										"url": {
											"raw": "{{baseUrl}}/api/person/v1/findPersonByName/:firstName?page=0&limit=12&direction=asc",
											"host": [
												"{{baseUrl}}"
											],
											"path": [
												"api",
												"person",
												"v1",
												"findPersonByName",
												":firstName"
											],
											"query": [
												{
													"key": "page",
													"value": "0"
												},
												{
													"key": "limit",
													"value": "12"
												},
												{
													"key": "direction",
													"value": "asc"
												}
											],
											"variable": [
												{
													"key": "firstName",
													"value": "id",
													"description": "(Required) "
												}
											]
										}
									},
									"status": "Unauthorized",
									"code": 401,
									"_postman_previewlanguage": "json",
									"header": [
										{
											"key": "Content-Type",
											"value": "application/json"
										}
									],
									"cookie": [],
									"body": "{}"
								},
								{
									"name": "Not Found",
									"originalRequest": {
										"method": "GET",
										"header": [],
										"url": {
											"raw": "{{baseUrl}}/api/person/v1/findPersonByName/:firstName?page=0&limit=12&direction=asc",
											"host": [
												"{{baseUrl}}"
											],
											"path": [
												"api",
												"person",
												"v1",
												"findPersonByName",
												":firstName"
											],
											"query": [
												{
													"key": "page",
													"value": "0"
												},
												{
													"key": "limit",
													"value": "12"
												},
												{
													"key": "direction",
													"value": "asc"
												}
											],
											"variable": [
												{
													"key": "firstName",
													"value": "id",
													"description": "(Required) "
												}
											]
										}
									},
									"status": "Not Found",
									"code": 404,
									"_postman_previewlanguage": "json",
									"header": [
										{
											"key": "Content-Type",
											"value": "application/json"
										}
									],
									"cookie": [],
									"body": "{}"
								},
								{
									"name": "Internal error",
									"originalRequest": {
										"method": "GET",
										"header": [],
										"url": {
											"raw": "{{baseUrl}}/api/person/v1/findPersonByName/:firstName?page=0&limit=12&direction=asc",
											"host": [
												"{{baseUrl}}"
											],
											"path": [
												"api",
												"person",
												"v1",
												"findPersonByName",
												":firstName"
											],
											"query": [
												{
													"key": "page",
													"value": "0"
												},
												{
													"key": "limit",
													"value": "12"
												},
												{
													"key": "direction",
													"value": "asc"
												}
											],
											"variable": [
												{
													"key": "firstName",
													"value": "id",
													"description": "(Required) "
												}
											]
										}
									},
									"status": "Internal Server Error",
									"code": 500,
									"_postman_previewlanguage": "json",
									"header": [
										{
											"key": "Content-Type",
											"value": "application/json"
										}
									],
									"cookie": [],
									"body": "{}"
								}
							]
						},
						{
							"name": "Finds a person",
							"request": {
								"method": "GET",
								"header": [
									{
										"key": "Accept",
										"value": "application/json"
									},
									{
										"key": "Authorization",
										"value": "Bearer {{refreshToken}}",
										"type": "text"
									}
								],
								"url": {
									"raw": "{{baseUrl}}/api/person/v1/:id",
									"host": [
										"{{baseUrl}}"
									],
									"path": [
										"api",
										"person",
										"v1",
										":id"
									],
									"variable": [
										{
											"key": "id",
											"value": "84900043",
											"description": "(Required) "
										}
									]
								},
								"description": "Find a specific person by your ID."
							},
							"response": [
								{
									"name": "Success",
									"originalRequest": {
										"method": "GET",
										"header": [],
										"url": {
											"raw": "{{baseUrl}}/api/person/v1/:id",
											"host": [
												"{{baseUrl}}"
											],
											"path": [
												"api",
												"person",
												"v1",
												":id"
											],
											"variable": [
												{
													"key": "id",
													"value": "84900043",
													"description": "(Required) "
												}
											]
										}
									},
									"status": "OK",
									"code": 200,
									"_postman_previewlanguage": "json",
									"header": [
										{
											"key": "Content-Type",
											"value": "application/json"
										}
									],
									"cookie": [],
									"body": "{\n  \"id\": 43259471,\n  \"firstName\": \"Lorem laborum velit reprehenderit\",\n  \"lastName\": \"officia anim\",\n  \"gender\": \"aliquip deserunt\",\n  \"address\": \"Lorem esse reprehenderit\",\n  \"enabled\": false,\n  \"_links\": {\n    \"irure13\": {\n      \"href\": \"deserunt tempor culpa dolor\",\n      \"hreflang\": \"exercitation veniam\",\n      \"title\": \"occaecat sint officia\",\n      \"type\": \"esse ea ipsum\",\n      \"deprecation\": \"n\",\n      \"profile\": \"dolor\",\n      \"name\": \"veniam in dolor ullamco\",\n      \"templated\": false\n    },\n    \"amet7c6\": {\n      \"href\": \"incididunt proident anim do\",\n      \"hreflang\": \"elit\",\n      \"title\": \"incididunt Lorem pariatur\",\n      \"type\": \"eu eiusmod\",\n      \"deprecation\": \"ipsum elit tempor quis\",\n      \"profile\": \"pariatur dolore\",\n      \"name\": \"officia aliquip ex\",\n      \"templated\": false\n    }\n  }\n}"
								},
								{
									"name": "No Content",
									"originalRequest": {
										"method": "GET",
										"header": [],
										"url": {
											"raw": "{{baseUrl}}/api/person/v1/:id",
											"host": [
												"{{baseUrl}}"
											],
											"path": [
												"api",
												"person",
												"v1",
												":id"
											],
											"variable": [
												{
													"key": "id",
													"value": "84900043",
													"description": "(Required) "
												}
											]
										}
									},
									"status": "No Content",
									"code": 204,
									"_postman_previewlanguage": "json",
									"header": [
										{
											"key": "Content-Type",
											"value": "application/json"
										}
									],
									"cookie": [],
									"body": "{}"
								},
								{
									"name": "Bad Request",
									"originalRequest": {
										"method": "GET",
										"header": [],
										"url": {
											"raw": "{{baseUrl}}/api/person/v1/:id",
											"host": [
												"{{baseUrl}}"
											],
											"path": [
												"api",
												"person",
												"v1",
												":id"
											],
											"variable": [
												{
													"key": "id",
													"value": "84900043",
													"description": "(Required) "
												}
											]
										}
									},
									"status": "Bad Request",
									"code": 400,
									"_postman_previewlanguage": "json",
									"header": [
										{
											"key": "Content-Type",
											"value": "application/json"
										}
									],
									"cookie": [],
									"body": "{}"
								},
								{
									"name": "Unauthorized",
									"originalRequest": {
										"method": "GET",
										"header": [],
										"url": {
											"raw": "{{baseUrl}}/api/person/v1/:id",
											"host": [
												"{{baseUrl}}"
											],
											"path": [
												"api",
												"person",
												"v1",
												":id"
											],
											"variable": [
												{
													"key": "id",
													"value": "84900043",
													"description": "(Required) "
												}
											]
										}
									},
									"status": "Unauthorized",
									"code": 401,
									"_postman_previewlanguage": "json",
									"header": [
										{
											"key": "Content-Type",
											"value": "application/json"
										}
									],
									"cookie": [],
									"body": "{}"
								},
								{
									"name": "Not Found",
									"originalRequest": {
										"method": "GET",
										"header": [],
										"url": {
											"raw": "{{baseUrl}}/api/person/v1/:id",
											"host": [
												"{{baseUrl}}"
											],
											"path": [
												"api",
												"person",
												"v1",
												":id"
											],
											"variable": [
												{
													"key": "id",
													"value": "84900043",
													"description": "(Required) "
												}
											]
										}
									},
									"status": "Not Found",
									"code": 404,
									"_postman_previewlanguage": "json",
									"header": [
										{
											"key": "Content-Type",
											"value": "application/json"
										}
									],
									"cookie": [],
									"body": "{}"
								},
								{
									"name": "Internal error",
									"originalRequest": {
										"method": "GET",
										"header": [],
										"url": {
											"raw": "{{baseUrl}}/api/person/v1/:id",
											"host": [
												"{{baseUrl}}"
											],
											"path": [
												"api",
												"person",
												"v1",
												":id"
											],
											"variable": [
												{
													"key": "id",
													"value": "84900043",
													"description": "(Required) "
												}
											]
										}
									},
									"status": "Internal Server Error",
									"code": 500,
									"_postman_previewlanguage": "json",
									"header": [
										{
											"key": "Content-Type",
											"value": "application/json"
										}
									],
									"cookie": [],
									"body": "{}"
								}
							]
						},
						{
							"name": "Updates a person's information",
							"request": {
								"method": "PUT",
								"header": [
									{
										"key": "Content-Type",
										"value": "application/json"
									},
									{
										"key": "Authorization",
										"value": "Bearer {{refreshToken}}",
										"type": "text"
									}
								],
								"body": {
									"mode": "raw",
									"raw": "{\n    \"id\": -97086494,\n    \"firstName\": \"dolore Excepteur\",\n    \"lastName\": \"exercitation esse consequat do\",\n    \"address\": \"nulla eu nisi voluptate ex\",\n    \"gender\": \"in sit minim\",\n    \"_links\": {}\n}",
									"options": {
										"raw": {
											"language": "json"
										}
									}
								},
								"url": {
									"raw": "{{baseUrl}}/api/person/v1",
									"host": [
										"{{baseUrl}}"
									],
									"path": [
										"api",
										"person",
										"v1"
									]
								},
								"description": "Updates a person's information by passing in a JSON, XML or YML representation of the updated person."
							},
							"response": [
								{
									"name": "Updated",
									"originalRequest": {
										"method": "PUT",
										"header": [],
										"body": {
											"mode": "raw",
											"raw": "{\n    \"id\": -97086494,\n    \"firstName\": \"dolore Excepteur\",\n    \"lastName\": \"exercitation esse consequat do\",\n    \"address\": \"nulla eu nisi voluptate ex\",\n    \"gender\": \"in sit minim\",\n    \"_links\": {}\n}",
											"options": {
												"raw": {
													"language": "json"
												}
											}
										},
										"url": {
											"raw": "{{baseUrl}}/api/person/v1",
											"host": [
												"{{baseUrl}}"
											],
											"path": [
												"api",
												"person",
												"v1"
											]
										}
									},
									"status": "OK",
									"code": 200,
									"_postman_previewlanguage": "json",
									"header": [
										{
											"key": "Content-Type",
											"value": "application/json"
										}
									],
									"cookie": [],
									"body": "{\n \"id\": -97086494,\n \"firstName\": \"dolore Excepteur\",\n \"lastName\": \"exercitation esse consequat do\",\n \"address\": \"nulla eu nisi voluptate ex\",\n \"gender\": \"in sit minim\",\n \"_links\": {}\n}"
								},
								{
									"name": "No Content",
									"originalRequest": {
										"method": "PUT",
										"header": [],
										"body": {
											"mode": "raw",
											"raw": "{\n    \"id\": -97086494,\n    \"firstName\": \"dolore Excepteur\",\n    \"lastName\": \"exercitation esse consequat do\",\n    \"address\": \"nulla eu nisi voluptate ex\",\n    \"gender\": \"in sit minim\",\n    \"_links\": {}\n}",
											"options": {
												"raw": {
													"language": "json"
												}
											}
										},
										"url": {
											"raw": "{{baseUrl}}/api/person/v1",
											"host": [
												"{{baseUrl}}"
											],
											"path": [
												"api",
												"person",
												"v1"
											]
										}
									},
									"status": "No Content",
									"code": 204,
									"_postman_previewlanguage": "json",
									"header": [
										{
											"key": "Content-Type",
											"value": "application/json"
										}
									],
									"cookie": [],
									"body": "{}"
								},
								{
									"name": "Bad Request",
									"originalRequest": {
										"method": "PUT",
										"header": [],
										"body": {
											"mode": "raw",
											"raw": "{\n    \"id\": -97086494,\n    \"firstName\": \"dolore Excepteur\",\n    \"lastName\": \"exercitation esse consequat do\",\n    \"address\": \"nulla eu nisi voluptate ex\",\n    \"gender\": \"in sit minim\",\n    \"_links\": {}\n}",
											"options": {
												"raw": {
													"language": "json"
												}
											}
										},
										"url": {
											"raw": "{{baseUrl}}/api/person/v1",
											"host": [
												"{{baseUrl}}"
											],
											"path": [
												"api",
												"person",
												"v1"
											]
										}
									},
									"status": "Bad Request",
									"code": 400,
									"_postman_previewlanguage": "json",
									"header": [
										{
											"key": "Content-Type",
											"value": "application/json"
										}
									],
									"cookie": [],
									"body": "{}"
								},
								{
									"name": "Unauthorized",
									"originalRequest": {
										"method": "PUT",
										"header": [],
										"body": {
											"mode": "raw",
											"raw": "{\n    \"id\": -97086494,\n    \"firstName\": \"dolore Excepteur\",\n    \"lastName\": \"exercitation esse consequat do\",\n    \"address\": \"nulla eu nisi voluptate ex\",\n    \"gender\": \"in sit minim\",\n    \"_links\": {}\n}",
											"options": {
												"raw": {
													"language": "json"
												}
											}
										},
										"url": {
											"raw": "{{baseUrl}}/api/person/v1",
											"host": [
												"{{baseUrl}}"
											],
											"path": [
												"api",
												"person",
												"v1"
											]
										}
									},
									"status": "Unauthorized",
									"code": 401,
									"_postman_previewlanguage": "json",
									"header": [
										{
											"key": "Content-Type",
											"value": "application/json"
										}
									],
									"cookie": [],
									"body": "{}"
								},
								{
									"name": "Not Found",
									"originalRequest": {
										"method": "PUT",
										"header": [],
										"body": {
											"mode": "raw",
											"raw": "{\n    \"id\": -97086494,\n    \"firstName\": \"dolore Excepteur\",\n    \"lastName\": \"exercitation esse consequat do\",\n    \"address\": \"nulla eu nisi voluptate ex\",\n    \"gender\": \"in sit minim\",\n    \"_links\": {}\n}",
											"options": {
												"raw": {
													"language": "json"
												}
											}
										},
										"url": {
											"raw": "{{baseUrl}}/api/person/v1",
											"host": [
												"{{baseUrl}}"
											],
											"path": [
												"api",
												"person",
												"v1"
											]
										}
									},
									"status": "Not Found",
									"code": 404,
									"_postman_previewlanguage": "json",
									"header": [
										{
											"key": "Content-Type",
											"value": "application/json"
										}
									],
									"cookie": [],
									"body": "{}"
								},
								{
									"name": "Internal error",
									"originalRequest": {
										"method": "PUT",
										"header": [],
										"body": {
											"mode": "raw",
											"raw": "{\n    \"id\": -97086494,\n    \"firstName\": \"dolore Excepteur\",\n    \"lastName\": \"exercitation esse consequat do\",\n    \"address\": \"nulla eu nisi voluptate ex\",\n    \"gender\": \"in sit minim\",\n    \"_links\": {}\n}",
											"options": {
												"raw": {
													"language": "json"
												}
											}
										},
										"url": {
											"raw": "{{baseUrl}}/api/person/v1",
											"host": [
												"{{baseUrl}}"
											],
											"path": [
												"api",
												"person",
												"v1"
											]
										}
									},
									"status": "Internal Server Error",
									"code": 500,
									"_postman_previewlanguage": "json",
									"header": [
										{
											"key": "Content-Type",
											"value": "application/json"
										}
									],
									"cookie": [],
									"body": "{}"
								}
							]
						},
						{
							"name": "Adds a new person",
							"request": {
								"method": "POST",
								"header": [
									{
										"key": "Content-Type",
										"value": "application/json"
									},
									{
										"key": "Authorization",
										"value": "Bearer {{refreshToken}}",
										"type": "text"
									}
								],
								"body": {
									"mode": "raw",
									"raw": "{\n    \"id\": -97086494,\n    \"firstName\": \"dolore Excepteur\",\n    \"lastName\": \"exercitation esse consequat do\",\n    \"address\": \"nulla eu nisi voluptate ex\",\n    \"gender\": \"in sit minim\",\n    \"_links\": {}\n}",
									"options": {
										"raw": {
											"language": "json"
										}
									}
								},
								"url": {
									"raw": "{{baseUrl}}/api/person/v1",
									"host": [
										"{{baseUrl}}"
									],
									"path": [
										"api",
										"person",
										"v1"
									]
								},
								"description": "Adds a new person by passing in a JSON, XML or YML representation of the person."
							},
							"response": [
								{
									"name": "Success",
									"originalRequest": {
										"method": "POST",
										"header": [],
										"body": {
											"mode": "raw",
											"raw": "{\n    \"id\": -97086494,\n    \"firstName\": \"dolore Excepteur\",\n    \"lastName\": \"exercitation esse consequat do\",\n    \"address\": \"nulla eu nisi voluptate ex\",\n    \"gender\": \"in sit minim\",\n    \"_links\": {}\n}",
											"options": {
												"raw": {
													"language": "json"
												}
											}
										},
										"url": {
											"raw": "{{baseUrl}}/api/person/v1",
											"host": [
												"{{baseUrl}}"
											],
											"path": [
												"api",
												"person",
												"v1"
											]
										}
									},
									"status": "OK",
									"code": 200,
									"_postman_previewlanguage": "json",
									"header": [
										{
											"key": "Content-Type",
											"value": "application/json"
										}
									],
									"cookie": [],
									"body": "{\n \"id\": -97086494,\n \"firstName\": \"dolore Excepteur\",\n \"lastName\": \"exercitation esse consequat do\",\n \"address\": \"nulla eu nisi voluptate ex\",\n \"gender\": \"in sit minim\",\n \"_links\": {}\n}"
								},
								{
									"name": "Bad Request",
									"originalRequest": {
										"method": "POST",
										"header": [],
										"body": {
											"mode": "raw",
											"raw": "{\n    \"id\": -97086494,\n    \"firstName\": \"dolore Excepteur\",\n    \"lastName\": \"exercitation esse consequat do\",\n    \"address\": \"nulla eu nisi voluptate ex\",\n    \"gender\": \"in sit minim\",\n    \"_links\": {}\n}",
											"options": {
												"raw": {
													"language": "json"
												}
											}
										},
										"url": {
											"raw": "{{baseUrl}}/api/person/v1",
											"host": [
												"{{baseUrl}}"
											],
											"path": [
												"api",
												"person",
												"v1"
											]
										}
									},
									"status": "Bad Request",
									"code": 400,
									"_postman_previewlanguage": "json",
									"header": [
										{
											"key": "Content-Type",
											"value": "application/json"
										}
									],
									"cookie": [],
									"body": "{}"
								},
								{
									"name": "Unauthorized",
									"originalRequest": {
										"method": "POST",
										"header": [],
										"body": {
											"mode": "raw",
											"raw": "{\n    \"id\": -97086494,\n    \"firstName\": \"dolore Excepteur\",\n    \"lastName\": \"exercitation esse consequat do\",\n    \"address\": \"nulla eu nisi voluptate ex\",\n    \"gender\": \"in sit minim\",\n    \"_links\": {}\n}",
											"options": {
												"raw": {
													"language": "json"
												}
											}
										},
										"url": {
											"raw": "{{baseUrl}}/api/person/v1",
											"host": [
												"{{baseUrl}}"
											],
											"path": [
												"api",
												"person",
												"v1"
											]
										}
									},
									"status": "Unauthorized",
									"code": 401,
									"_postman_previewlanguage": "json",
									"header": [
										{
											"key": "Content-Type",
											"value": "application/json"
										}
									],
									"cookie": [],
									"body": "{}"
								},
								{
									"name": "Internal error",
									"originalRequest": {
										"method": "POST",
										"header": [],
										"body": {
											"mode": "raw",
											"raw": "{\n    \"id\": -97086494,\n    \"firstName\": \"dolore Excepteur\",\n    \"lastName\": \"exercitation esse consequat do\",\n    \"address\": \"nulla eu nisi voluptate ex\",\n    \"gender\": \"in sit minim\",\n    \"_links\": {}\n}",
											"options": {
												"raw": {
													"language": "json"
												}
											}
										},
										"url": {
											"raw": "{{baseUrl}}/api/person/v1",
											"host": [
												"{{baseUrl}}"
											],
											"path": [
												"api",
												"person",
												"v1"
											]
										}
									},
									"status": "Internal Server Error",
									"code": 500,
									"_postman_previewlanguage": "json",
									"header": [
										{
											"key": "Content-Type",
											"value": "application/json"
										}
									],
									"cookie": [],
									"body": "{}"
								}
							]
						},
						{
							"name": "Disable a person",
							"request": {
								"method": "PATCH",
								"header": [
									{
										"key": "Authorization",
										"value": "Bearer {{refreshToken}}",
										"type": "text"
									}
								],
								"url": {
									"raw": "{{baseUrl}}/api/person/v1/1",
									"host": [
										"{{baseUrl}}"
									],
									"path": [
										"api",
										"person",
										"v1",
										"1"
									]
								},
								"description": "Find a specific person by your ID."
							},
							"response": [
								{
									"name": "Success",
									"originalRequest": {
										"method": "GET",
										"header": [],
										"url": {
											"raw": "{{baseUrl}}/api/person/v1/:id",
											"host": [
												"{{baseUrl}}"
											],
											"path": [
												"api",
												"person",
												"v1",
												":id"
											],
											"variable": [
												{
													"key": "id",
													"value": "98161935",
													"description": "(Required) "
												}
											]
										}
									},
									"status": "OK",
									"code": 200,
									"_postman_previewlanguage": "json",
									"header": [
										{
											"key": "Content-Type",
											"value": "application/json"
										}
									],
									"cookie": [],
									"body": "{\n \"id\": -97086494,\n \"firstName\": \"dolore Excepteur\",\n \"lastName\": \"exercitation esse consequat do\",\n \"address\": \"nulla eu nisi voluptate ex\",\n \"gender\": \"in sit minim\",\n \"_links\": {}\n}"
								},
								{
									"name": "No Content",
									"originalRequest": {
										"method": "GET",
										"header": [],
										"url": {
											"raw": "{{baseUrl}}/api/person/v1/:id",
											"host": [
												"{{baseUrl}}"
											],
											"path": [
												"api",
												"person",
												"v1",
												":id"
											],
											"variable": [
												{
													"key": "id",
													"value": "98161935",
													"description": "(Required) "
												}
											]
										}
									},
									"status": "No Content",
									"code": 204,
									"_postman_previewlanguage": "json",
									"header": [
										{
											"key": "Content-Type",
											"value": "application/json"
										}
									],
									"cookie": [],
									"body": "{}"
								},
								{
									"name": "Bad Request",
									"originalRequest": {
										"method": "GET",
										"header": [],
										"url": {
											"raw": "{{baseUrl}}/api/person/v1/:id",
											"host": [
												"{{baseUrl}}"
											],
											"path": [
												"api",
												"person",
												"v1",
												":id"
											],
											"variable": [
												{
													"key": "id",
													"value": "98161935",
													"description": "(Required) "
												}
											]
										}
									},
									"status": "Bad Request",
									"code": 400,
									"_postman_previewlanguage": "json",
									"header": [
										{
											"key": "Content-Type",
											"value": "application/json"
										}
									],
									"cookie": [],
									"body": "{}"
								},
								{
									"name": "Unauthorized",
									"originalRequest": {
										"method": "GET",
										"header": [],
										"url": {
											"raw": "{{baseUrl}}/api/person/v1/:id",
											"host": [
												"{{baseUrl}}"
											],
											"path": [
												"api",
												"person",
												"v1",
												":id"
											],
											"variable": [
												{
													"key": "id",
													"value": "98161935",
													"description": "(Required) "
												}
											]
										}
									},
									"status": "Unauthorized",
									"code": 401,
									"_postman_previewlanguage": "json",
									"header": [
										{
											"key": "Content-Type",
											"value": "application/json"
										}
									],
									"cookie": [],
									"body": "{}"
								},
								{
									"name": "Not Found",
									"originalRequest": {
										"method": "GET",
										"header": [],
										"url": {
											"raw": "{{baseUrl}}/api/person/v1/:id",
											"host": [
												"{{baseUrl}}"
											],
											"path": [
												"api",
												"person",
												"v1",
												":id"
											],
											"variable": [
												{
													"key": "id",
													"value": "98161935",
													"description": "(Required) "
												}
											]
										}
									},
									"status": "Not Found",
									"code": 404,
									"_postman_previewlanguage": "json",
									"header": [
										{
											"key": "Content-Type",
											"value": "application/json"
										}
									],
									"cookie": [],
									"body": "{}"
								},
								{
									"name": "Internal error",
									"originalRequest": {
										"method": "GET",
										"header": [],
										"url": {
											"raw": "{{baseUrl}}/api/person/v1/:id",
											"host": [
												"{{baseUrl}}"
											],
											"path": [
												"api",
												"person",
												"v1",
												":id"
											],
											"variable": [
												{
													"key": "id",
													"value": "98161935",
													"description": "(Required) "
												}
											]
										}
									},
									"status": "Internal Server Error",
									"code": 500,
									"_postman_previewlanguage": "json",
									"header": [
										{
											"key": "Content-Type",
											"value": "application/json"
										}
									],
									"cookie": [],
									"body": "{}"
								}
							]
						},
						{
							"name": "Deletes a person",
							"request": {
								"method": "DELETE",
								"header": [
									{
										"key": "Authorization",
										"value": "Bearer {{refreshToken}}",
										"type": "text"
									}
								],
								"url": {
									"raw": "{{baseUrl}}/api/person/v1/:id",
									"host": [
										"{{baseUrl}}"
									],
									"path": [
										"api",
										"person",
										"v1",
										":id"
									],
									"variable": [
										{
											"key": "id",
											"value": "98161935",
											"description": "(Required) "
										}
									]
								},
								"description": "Deletes a person by their Id."
							},
							"response": [
								{
									"name": "No Content",
									"originalRequest": {
										"method": "DELETE",
										"header": [],
										"url": {
											"raw": "{{baseUrl}}/api/person/v1/:id",
											"host": [
												"{{baseUrl}}"
											],
											"path": [
												"api",
												"person",
												"v1",
												":id"
											],
											"variable": [
												{
													"key": "id",
													"value": "98161935",
													"description": "(Required) "
												}
											]
										}
									},
									"status": "No Content",
									"code": 204,
									"_postman_previewlanguage": "json",
									"header": [
										{
											"key": "Content-Type",
											"value": "application/hal+json"
										}
									],
									"cookie": [],
									"body": "{}"
								},
								{
									"name": "Bad Request",
									"originalRequest": {
										"method": "DELETE",
										"header": [],
										"url": {
											"raw": "{{baseUrl}}/api/person/v1/:id",
											"host": [
												"{{baseUrl}}"
											],
											"path": [
												"api",
												"person",
												"v1",
												":id"
											],
											"variable": [
												{
													"key": "id",
													"value": "98161935",
													"description": "(Required) "
												}
											]
										}
									},
									"status": "Bad Request",
									"code": 400,
									"_postman_previewlanguage": "json",
									"header": [
										{
											"key": "Content-Type",
											"value": "application/hal+json"
										}
									],
									"cookie": [],
									"body": "{}"
								},
								{
									"name": "Unauthorized",
									"originalRequest": {
										"method": "DELETE",
										"header": [],
										"url": {
											"raw": "{{baseUrl}}/api/person/v1/:id",
											"host": [
												"{{baseUrl}}"
											],
											"path": [
												"api",
												"person",
												"v1",
												":id"
											],
											"variable": [
												{
													"key": "id",
													"value": "98161935",
													"description": "(Required) "
												}
											]
										}
									},
									"status": "Unauthorized",
									"code": 401,
									"_postman_previewlanguage": "json",
									"header": [
										{
											"key": "Content-Type",
											"value": "application/hal+json"
										}
									],
									"cookie": [],
									"body": "{}"
								},
								{
									"name": "Not Found",
									"originalRequest": {
										"method": "DELETE",
										"header": [],
										"url": {
											"raw": "{{baseUrl}}/api/person/v1/:id",
											"host": [
												"{{baseUrl}}"
											],
											"path": [
												"api",
												"person",
												"v1",
												":id"
											],
											"variable": [
												{
													"key": "id",
													"value": "98161935",
													"description": "(Required) "
												}
											]
										}
									},
									"status": "Not Found",
									"code": 404,
									"_postman_previewlanguage": "json",
									"header": [
										{
											"key": "Content-Type",
											"value": "application/hal+json"
										}
									],
									"cookie": [],
									"body": "{}"
								},
								{
									"name": "Internal error",
									"originalRequest": {
										"method": "DELETE",
										"header": [],
										"url": {
											"raw": "{{baseUrl}}/api/person/v1/:id",
											"host": [
												"{{baseUrl}}"
											],
											"path": [
												"api",
												"person",
												"v1",
												":id"
											],
											"variable": [
												{
													"key": "id",
													"value": "98161935",
													"description": "(Required) "
												}
											]
										}
									},
									"status": "Internal Server Error",
									"code": 500,
									"_postman_previewlanguage": "json",
									"header": [
										{
											"key": "Content-Type",
											"value": "application/hal+json"
										}
									],
									"cookie": [],
									"body": "{}"
								}
							]
						}
					]
				},
				{
					"name": "book/v1",
					"item": [
						{
							"name": "Finds all Book",
							"request": {
								"method": "GET",
								"header": [
									{
										"key": "Accept",
										"value": "application/json"
									},
									{
										"key": "Authorization",
										"value": "Bearer {{refreshToken}}",
										"type": "text"
									}
								],
								"url": {
									"raw": "{{baseUrl}}/api/book/v1?page=0&limit=12&direction=asc",
									"host": [
										"{{baseUrl}}"
									],
									"path": [
										"api",
										"book",
										"v1"
									],
									"query": [
										{
											"key": "page",
											"value": "0"
										},
										{
											"key": "limit",
											"value": "12"
										},
										{
											"key": "direction",
											"value": "asc"
										}
									]
								},
								"description": "Finds all Book."
							},
							"response": [
								{
									"name": "Success",
									"originalRequest": {
										"method": "GET",
										"header": [],
										"url": {
											"raw": "{{baseUrl}}/api/book/v1?page=0&limit=12&direction=asc",
											"host": [
												"{{baseUrl}}"
											],
											"path": [
												"api",
												"book",
												"v1"
											],
											"query": [
												{
													"key": "page",
													"value": "0"
												},
												{
													"key": "limit",
													"value": "12"
												},
												{
													"key": "direction",
													"value": "asc"
												}
											]
										}
									},
									"status": "OK",
									"code": 200,
									"_postman_previewlanguage": "json",
									"header": [
										{
											"key": "Content-Type",
											"value": "application/json"
										}
									],
									"cookie": [],
									"body": "[\n  {\n    \"id\": -86976786,\n    \"author\": \"dolor occaecat ad dolor\",\n    \"launchDate\": \"2020-04-30T14:42:33.034Z\",\n    \"price\": 20935656.7080957,\n    \"title\": \"eiusmod eu sit\",\n    \"_links\": {\n      \"proident_a\": {\n        \"href\": \"fugiat \",\n        \"hreflang\": \"nisi exercitation pariatur\",\n        \"title\": \"voluptate ipsum paria\",\n        \"type\": \"in amet\",\n        \"deprecation\": \"eiusmod dolore\",\n        \"profile\": \"do\",\n        \"name\": \"dolor dolore labore\",\n        \"templated\": true\n      },\n      \"dolorb_e\": {\n        \"href\": \"quis\",\n        \"hreflang\": \"adipisicing fugiat volupt\",\n        \"title\": \"ex exercitation\",\n        \"type\": \"aliqua voluptate commodo consectetur tempor\",\n        \"deprecation\": \"quis ut est\",\n        \"profile\": \"elit aute tempor nostrud ad\",\n        \"name\": \"nostr\",\n        \"templated\": false\n      },\n      \"ullamco_98\": {\n        \"href\": \"laboris est\",\n        \"hreflang\": \"officia eiusmod dolor\",\n        \"title\": \"consequat deserunt cillum ut\",\n        \"type\": \"aute sunt occaecat Lorem\",\n        \"deprecation\": \"ipsu\",\n        \"profile\": \"Duis\",\n        \"name\": \"voluptate sit \",\n        \"templated\": false\n      }\n    }\n  },\n  {\n    \"id\": -70513132,\n    \"author\": \"ad in sit consequat adip\",\n    \"launchDate\": \"1944-06-18T08:33:52.029Z\",\n    \"price\": -25957122.021655858,\n    \"title\": \"et fugiat\",\n    \"_links\": {\n      \"culpa_5b\": {\n        \"href\": \"dolore sunt laborum qui consequat\",\n        \"hreflang\": \"exercitation labore deserunt\",\n        \"title\": \"sed qui cillum\",\n        \"type\": \"ea cupida\",\n        \"deprecation\": \"nulla in aliqua ad\",\n        \"profile\": \"qui aute ad eiusmod laborum\",\n        \"name\": \"ut\",\n        \"templated\": false\n      },\n      \"tempor440\": {\n        \"href\": \"ut est cupidatat\",\n        \"hreflang\": \"nulla ut adipisicing deserunt\",\n        \"title\": \"laborum occaecat irure sit elit\",\n        \"type\": \"culpa occaecat exercitation deserunt\",\n        \"deprecation\": \"nulla dolore deserunt eiusmod\",\n        \"profile\": \"fugiat et\",\n        \"name\": \"ullamco in dolore Excepteur\",\n        \"templated\": false\n      }\n    }\n  }\n]"
								},
								{
									"name": "No Content",
									"originalRequest": {
										"method": "GET",
										"header": [],
										"url": {
											"raw": "{{baseUrl}}/api/book/v1?page=0&limit=12&direction=asc",
											"host": [
												"{{baseUrl}}"
											],
											"path": [
												"api",
												"book",
												"v1"
											],
											"query": [
												{
													"key": "page",
													"value": "0"
												},
												{
													"key": "limit",
													"value": "12"
												},
												{
													"key": "direction",
													"value": "asc"
												}
											]
										}
									},
									"status": "No Content",
									"code": 204,
									"_postman_previewlanguage": "json",
									"header": [
										{
											"key": "Content-Type",
											"value": "application/json"
										}
									],
									"cookie": [],
									"body": "{}"
								},
								{
									"name": "Bad Request",
									"originalRequest": {
										"method": "GET",
										"header": [],
										"url": {
											"raw": "{{baseUrl}}/api/book/v1?page=0&limit=12&direction=asc",
											"host": [
												"{{baseUrl}}"
											],
											"path": [
												"api",
												"book",
												"v1"
											],
											"query": [
												{
													"key": "page",
													"value": "0"
												},
												{
													"key": "limit",
													"value": "12"
												},
												{
													"key": "direction",
													"value": "asc"
												}
											]
										}
									},
									"status": "Bad Request",
									"code": 400,
									"_postman_previewlanguage": "json",
									"header": [
										{
											"key": "Content-Type",
											"value": "application/json"
										}
									],
									"cookie": [],
									"body": "{}"
								},
								{
									"name": "Unauthorized",
									"originalRequest": {
										"method": "GET",
										"header": [],
										"url": {
											"raw": "{{baseUrl}}/api/book/v1?page=0&limit=12&direction=asc",
											"host": [
												"{{baseUrl}}"
											],
											"path": [
												"api",
												"book",
												"v1"
											],
											"query": [
												{
													"key": "page",
													"value": "0"
												},
												{
													"key": "limit",
													"value": "12"
												},
												{
													"key": "direction",
													"value": "asc"
												}
											]
										}
									},
									"status": "Unauthorized",
									"code": 401,
									"_postman_previewlanguage": "json",
									"header": [
										{
											"key": "Content-Type",
											"value": "application/json"
										}
									],
									"cookie": [],
									"body": "{}"
								},
								{
									"name": "Not Found",
									"originalRequest": {
										"method": "GET",
										"header": [],
										"url": {
											"raw": "{{baseUrl}}/api/book/v1?page=0&limit=12&direction=asc",
											"host": [
												"{{baseUrl}}"
											],
											"path": [
												"api",
												"book",
												"v1"
											],
											"query": [
												{
													"key": "page",
													"value": "0"
												},
												{
													"key": "limit",
													"value": "12"
												},
												{
													"key": "direction",
													"value": "asc"
												}
											]
										}
									},
									"status": "Not Found",
									"code": 404,
									"_postman_previewlanguage": "json",
									"header": [
										{
											"key": "Content-Type",
											"value": "application/json"
										}
									],
									"cookie": [],
									"body": "{}"
								},
								{
									"name": "Internal error",
									"originalRequest": {
										"method": "GET",
										"header": [],
										"url": {
											"raw": "{{baseUrl}}/api/book/v1?page=0&limit=12&direction=asc",
											"host": [
												"{{baseUrl}}"
											],
											"path": [
												"api",
												"book",
												"v1"
											],
											"query": [
												{
													"key": "page",
													"value": "0"
												},
												{
													"key": "limit",
													"value": "12"
												},
												{
													"key": "direction",
													"value": "asc"
												}
											]
										}
									},
									"status": "Internal Server Error",
									"code": 500,
									"_postman_previewlanguage": "json",
									"header": [
										{
											"key": "Content-Type",
											"value": "application/json"
										}
									],
									"cookie": [],
									"body": "{}"
								}
							]
						},
						{
							"name": "Finds a book",
							"request": {
								"method": "GET",
								"header": [
									{
										"key": "Accept",
										"value": "application/json"
									},
									{
										"key": "Authorization",
										"value": "Bearer {{refreshToken}}",
										"type": "text"
									}
								],
								"url": {
									"raw": "{{baseUrl}}/api/book/v1/:id",
									"host": [
										"{{baseUrl}}"
									],
									"path": [
										"api",
										"book",
										"v1",
										":id"
									],
									"variable": [
										{
											"key": "id",
											"value": "84900043",
											"description": "(Required) "
										}
									]
								},
								"description": "Find a specific book by your ID."
							},
							"response": [
								{
									"name": "Success",
									"originalRequest": {
										"method": "GET",
										"header": [],
										"url": {
											"raw": "{{baseUrl}}/api/book/v1/:id",
											"host": [
												"{{baseUrl}}"
											],
											"path": [
												"api",
												"book",
												"v1",
												":id"
											],
											"variable": [
												{
													"key": "id",
													"value": "84900043",
													"description": "(Required) "
												}
											]
										}
									},
									"status": "OK",
									"code": 200,
									"_postman_previewlanguage": "json",
									"header": [
										{
											"key": "Content-Type",
											"value": "application/json"
										}
									],
									"cookie": [],
									"body": "{\n  \"id\": 18636880,\n  \"author\": \"aute nulla consectetur\",\n  \"launchDate\": \"2004-08-16T17:11:07.459Z\",\n  \"price\": 32956529.757331938,\n  \"title\": \"ut \",\n  \"_links\": {\n    \"non5\": {\n      \"href\": \"esse\",\n      \"hreflang\": \"in dolor\",\n      \"title\": \"dolor Lorem\",\n      \"type\": \"enim aliqua in dolor cillum\",\n      \"deprecation\": \"in magna commodo\",\n      \"profile\": \"deserunt ex cupidatat in\",\n      \"name\": \"minim\",\n      \"templated\": false\n    },\n    \"dolor_ac\": {\n      \"href\": \"dolor est mollit\",\n      \"hreflang\": \"proident Ut\",\n      \"title\": \"esse nostrud\",\n      \"type\": \"ullamco irure\",\n      \"deprecation\": \"Duis incididunt do\",\n      \"profile\": \"labore sint elit\",\n      \"name\": \"non velit consequat dolore\",\n      \"templated\": true\n    }\n  }\n}"
								},
								{
									"name": "No Content",
									"originalRequest": {
										"method": "GET",
										"header": [],
										"url": {
											"raw": "{{baseUrl}}/api/book/v1/:id",
											"host": [
												"{{baseUrl}}"
											],
											"path": [
												"api",
												"book",
												"v1",
												":id"
											],
											"variable": [
												{
													"key": "id",
													"value": "84900043",
													"description": "(Required) "
												}
											]
										}
									},
									"status": "No Content",
									"code": 204,
									"_postman_previewlanguage": "json",
									"header": [
										{
											"key": "Content-Type",
											"value": "application/json"
										}
									],
									"cookie": [],
									"body": "{}"
								},
								{
									"name": "Bad Request",
									"originalRequest": {
										"method": "GET",
										"header": [],
										"url": {
											"raw": "{{baseUrl}}/api/book/v1/:id",
											"host": [
												"{{baseUrl}}"
											],
											"path": [
												"api",
												"book",
												"v1",
												":id"
											],
											"variable": [
												{
													"key": "id",
													"value": "84900043",
													"description": "(Required) "
												}
											]
										}
									},
									"status": "Bad Request",
									"code": 400,
									"_postman_previewlanguage": "json",
									"header": [
										{
											"key": "Content-Type",
											"value": "application/json"
										}
									],
									"cookie": [],
									"body": "{}"
								},
								{
									"name": "Unauthorized",
									"originalRequest": {
										"method": "GET",
										"header": [],
										"url": {
											"raw": "{{baseUrl}}/api/book/v1/:id",
											"host": [
												"{{baseUrl}}"
											],
											"path": [
												"api",
												"book",
												"v1",
												":id"
											],
											"variable": [
												{
													"key": "id",
													"value": "84900043",
													"description": "(Required) "
												}
											]
										}
									},
									"status": "Unauthorized",
									"code": 401,
									"_postman_previewlanguage": "json",
									"header": [
										{
											"key": "Content-Type",
											"value": "application/json"
										}
									],
									"cookie": [],
									"body": "{}"
								},
								{
									"name": "Not Found",
									"originalRequest": {
										"method": "GET",
										"header": [],
										"url": {
											"raw": "{{baseUrl}}/api/book/v1/:id",
											"host": [
												"{{baseUrl}}"
											],
											"path": [
												"api",
												"book",
												"v1",
												":id"
											],
											"variable": [
												{
													"key": "id",
													"value": "84900043",
													"description": "(Required) "
												}
											]
										}
									},
									"status": "Not Found",
									"code": 404,
									"_postman_previewlanguage": "json",
									"header": [
										{
											"key": "Content-Type",
											"value": "application/json"
										}
									],
									"cookie": [],
									"body": "{}"
								},
								{
									"name": "Internal error",
									"originalRequest": {
										"method": "GET",
										"header": [],
										"url": {
											"raw": "{{baseUrl}}/api/book/v1/:id",
											"host": [
												"{{baseUrl}}"
											],
											"path": [
												"api",
												"book",
												"v1",
												":id"
											],
											"variable": [
												{
													"key": "id",
													"value": "84900043",
													"description": "(Required) "
												}
											]
										}
									},
									"status": "Internal Server Error",
									"code": 500,
									"_postman_previewlanguage": "json",
									"header": [
										{
											"key": "Content-Type",
											"value": "application/json"
										}
									],
									"cookie": [],
									"body": "{}"
								}
							]
						},
						{
							"name": "Updates a book's information",
							"request": {
								"method": "PUT",
								"header": [
									{
										"key": "Content-Type",
										"value": "application/json"
									},
									{
										"key": "Authorization",
										"value": "Bearer {{refreshToken}}",
										"type": "text"
									}
								],
								"body": {
									"mode": "raw",
									"raw": "{\n    \"id\": 58506145,\n    \"author\": \"amet id cupi\",\n    \"launchDate\": \"1988-07-04T06:28:50.279Z\",\n    \"price\": 79309139.85579339,\n    \"title\": \"Excepteur commodo irure mollit\",\n    \"_links\": {}\n}",
									"options": {
										"raw": {
											"language": "json"
										}
									}
								},
								"url": {
									"raw": "{{baseUrl}}/api/book/v1",
									"host": [
										"{{baseUrl}}"
									],
									"path": [
										"api",
										"book",
										"v1"
									]
								},
								"description": "Updates a book's information by passing in a JSON, XML or YML representation of the updated book."
							},
							"response": [
								{
									"name": "Updated",
									"originalRequest": {
										"method": "PUT",
										"header": [],
										"body": {
											"mode": "raw",
											"raw": "{\n    \"id\": 58506145,\n    \"author\": \"amet id cupi\",\n    \"launchDate\": \"1988-07-04T06:28:50.279Z\",\n    \"price\": 79309139.85579339,\n    \"title\": \"Excepteur commodo irure mollit\",\n    \"_links\": {}\n}",
											"options": {
												"raw": {
													"language": "json"
												}
											}
										},
										"url": {
											"raw": "{{baseUrl}}/api/book/v1",
											"host": [
												"{{baseUrl}}"
											],
											"path": [
												"api",
												"book",
												"v1"
											]
										}
									},
									"status": "OK",
									"code": 200,
									"_postman_previewlanguage": "json",
									"header": [
										{
											"key": "Content-Type",
											"value": "application/json"
										}
									],
									"cookie": [],
									"body": "{\n \"id\": 58506145,\n \"author\": \"amet id cupi\",\n \"launchDate\": \"1988-07-04T06:28:50.279Z\",\n \"price\": 79309139.85579339,\n \"title\": \"Excepteur commodo irure mollit\",\n \"_links\": {}\n}"
								},
								{
									"name": "No Content",
									"originalRequest": {
										"method": "PUT",
										"header": [],
										"body": {
											"mode": "raw",
											"raw": "{\n    \"id\": 58506145,\n    \"author\": \"amet id cupi\",\n    \"launchDate\": \"1988-07-04T06:28:50.279Z\",\n    \"price\": 79309139.85579339,\n    \"title\": \"Excepteur commodo irure mollit\",\n    \"_links\": {}\n}",
											"options": {
												"raw": {
													"language": "json"
												}
											}
										},
										"url": {
											"raw": "{{baseUrl}}/api/book/v1",
											"host": [
												"{{baseUrl}}"
											],
											"path": [
												"api",
												"book",
												"v1"
											]
										}
									},
									"status": "No Content",
									"code": 204,
									"_postman_previewlanguage": "json",
									"header": [
										{
											"key": "Content-Type",
											"value": "application/json"
										}
									],
									"cookie": [],
									"body": "{}"
								},
								{
									"name": "Bad Request",
									"originalRequest": {
										"method": "PUT",
										"header": [],
										"body": {
											"mode": "raw",
											"raw": "{\n    \"id\": 58506145,\n    \"author\": \"amet id cupi\",\n    \"launchDate\": \"1988-07-04T06:28:50.279Z\",\n    \"price\": 79309139.85579339,\n    \"title\": \"Excepteur commodo irure mollit\",\n    \"_links\": {}\n}",
											"options": {
												"raw": {
													"language": "json"
												}
											}
										},
										"url": {
											"raw": "{{baseUrl}}/api/book/v1",
											"host": [
												"{{baseUrl}}"
											],
											"path": [
												"api",
												"book",
												"v1"
											]
										}
									},
									"status": "Bad Request",
									"code": 400,
									"_postman_previewlanguage": "json",
									"header": [
										{
											"key": "Content-Type",
											"value": "application/json"
										}
									],
									"cookie": [],
									"body": "{}"
								},
								{
									"name": "Unauthorized",
									"originalRequest": {
										"method": "PUT",
										"header": [],
										"body": {
											"mode": "raw",
											"raw": "{\n    \"id\": 58506145,\n    \"author\": \"amet id cupi\",\n    \"launchDate\": \"1988-07-04T06:28:50.279Z\",\n    \"price\": 79309139.85579339,\n    \"title\": \"Excepteur commodo irure mollit\",\n    \"_links\": {}\n}",
											"options": {
												"raw": {
													"language": "json"
												}
											}
										},
										"url": {
											"raw": "{{baseUrl}}/api/book/v1",
											"host": [
												"{{baseUrl}}"
											],
											"path": [
												"api",
												"book",
												"v1"
											]
										}
									},
									"status": "Unauthorized",
									"code": 401,
									"_postman_previewlanguage": "json",
									"header": [
										{
											"key": "Content-Type",
											"value": "application/json"
										}
									],
									"cookie": [],
									"body": "{}"
								},
								{
									"name": "Not Found",
									"originalRequest": {
										"method": "PUT",
										"header": [],
										"body": {
											"mode": "raw",
											"raw": "{\n    \"id\": 58506145,\n    \"author\": \"amet id cupi\",\n    \"launchDate\": \"1988-07-04T06:28:50.279Z\",\n    \"price\": 79309139.85579339,\n    \"title\": \"Excepteur commodo irure mollit\",\n    \"_links\": {}\n}",
											"options": {
												"raw": {
													"language": "json"
												}
											}
										},
										"url": {
											"raw": "{{baseUrl}}/api/book/v1",
											"host": [
												"{{baseUrl}}"
											],
											"path": [
												"api",
												"book",
												"v1"
											]
										}
									},
									"status": "Not Found",
									"code": 404,
									"_postman_previewlanguage": "json",
									"header": [
										{
											"key": "Content-Type",
											"value": "application/json"
										}
									],
									"cookie": [],
									"body": "{}"
								},
								{
									"name": "Internal error",
									"originalRequest": {
										"method": "PUT",
										"header": [],
										"body": {
											"mode": "raw",
											"raw": "{\n    \"id\": 58506145,\n    \"author\": \"amet id cupi\",\n    \"launchDate\": \"1988-07-04T06:28:50.279Z\",\n    \"price\": 79309139.85579339,\n    \"title\": \"Excepteur commodo irure mollit\",\n    \"_links\": {}\n}",
											"options": {
												"raw": {
													"language": "json"
												}
											}
										},
										"url": {
											"raw": "{{baseUrl}}/api/book/v1",
											"host": [
												"{{baseUrl}}"
											],
											"path": [
												"api",
												"book",
												"v1"
											]
										}
									},
									"status": "Internal Server Error",
									"code": 500,
									"_postman_previewlanguage": "json",
									"header": [
										{
											"key": "Content-Type",
											"value": "application/json"
										}
									],
									"cookie": [],
									"body": "{}"
								}
							]
						},
						{
							"name": "Adds a new book",
							"request": {
								"method": "POST",
								"header": [
									{
										"key": "Content-Type",
										"value": "application/json"
									},
									{
										"key": "Authorization",
										"value": "Bearer {{refreshToken}}",
										"type": "text"
									}
								],
								"body": {
									"mode": "raw",
									"raw": "{\n    \"id\": 58506145,\n    \"author\": \"amet id cupi\",\n    \"launchDate\": \"1988-07-04T06:28:50.279Z\",\n    \"price\": 79309139.85579339,\n    \"title\": \"Excepteur commodo irure mollit\",\n    \"_links\": {}\n}",
									"options": {
										"raw": {
											"language": "json"
										}
									}
								},
								"url": {
									"raw": "{{baseUrl}}/api/book/v1",
									"host": [
										"{{baseUrl}}"
									],
									"path": [
										"api",
										"book",
										"v1"
									]
								},
								"description": "Adds a new book by passing in a JSON, XML or YML representation of the book."
							},
							"response": [
								{
									"name": "Success",
									"originalRequest": {
										"method": "POST",
										"header": [],
										"body": {
											"mode": "raw",
											"raw": "{\n    \"id\": 58506145,\n    \"author\": \"amet id cupi\",\n    \"launchDate\": \"1988-07-04T06:28:50.279Z\",\n    \"price\": 79309139.85579339,\n    \"title\": \"Excepteur commodo irure mollit\",\n    \"_links\": {}\n}",
											"options": {
												"raw": {
													"language": "json"
												}
											}
										},
										"url": {
											"raw": "{{baseUrl}}/api/book/v1",
											"host": [
												"{{baseUrl}}"
											],
											"path": [
												"api",
												"book",
												"v1"
											]
										}
									},
									"status": "OK",
									"code": 200,
									"_postman_previewlanguage": "json",
									"header": [
										{
											"key": "Content-Type",
											"value": "application/json"
										}
									],
									"cookie": [],
									"body": "{\n \"id\": 58506145,\n \"author\": \"amet id cupi\",\n \"launchDate\": \"1988-07-04T06:28:50.279Z\",\n \"price\": 79309139.85579339,\n \"title\": \"Excepteur commodo irure mollit\",\n \"_links\": {}\n}"
								},
								{
									"name": "Bad Request",
									"originalRequest": {
										"method": "POST",
										"header": [],
										"body": {
											"mode": "raw",
											"raw": "{\n    \"id\": 58506145,\n    \"author\": \"amet id cupi\",\n    \"launchDate\": \"1988-07-04T06:28:50.279Z\",\n    \"price\": 79309139.85579339,\n    \"title\": \"Excepteur commodo irure mollit\",\n    \"_links\": {}\n}",
											"options": {
												"raw": {
													"language": "json"
												}
											}
										},
										"url": {
											"raw": "{{baseUrl}}/api/book/v1",
											"host": [
												"{{baseUrl}}"
											],
											"path": [
												"api",
												"book",
												"v1"
											]
										}
									},
									"status": "Bad Request",
									"code": 400,
									"_postman_previewlanguage": "json",
									"header": [
										{
											"key": "Content-Type",
											"value": "application/json"
										}
									],
									"cookie": [],
									"body": "{}"
								},
								{
									"name": "Unauthorized",
									"originalRequest": {
										"method": "POST",
										"header": [],
										"body": {
											"mode": "raw",
											"raw": "{\n    \"id\": 58506145,\n    \"author\": \"amet id cupi\",\n    \"launchDate\": \"1988-07-04T06:28:50.279Z\",\n    \"price\": 79309139.85579339,\n    \"title\": \"Excepteur commodo irure mollit\",\n    \"_links\": {}\n}",
											"options": {
												"raw": {
													"language": "json"
												}
											}
										},
										"url": {
											"raw": "{{baseUrl}}/api/book/v1",
											"host": [
												"{{baseUrl}}"
											],
											"path": [
												"api",
												"book",
												"v1"
											]
										}
									},
									"status": "Unauthorized",
									"code": 401,
									"_postman_previewlanguage": "json",
									"header": [
										{
											"key": "Content-Type",
											"value": "application/json"
										}
									],
									"cookie": [],
									"body": "{}"
								},
								{
									"name": "Internal error",
									"originalRequest": {
										"method": "POST",
										"header": [],
										"body": {
											"mode": "raw",
											"raw": "{\n    \"id\": 58506145,\n    \"author\": \"amet id cupi\",\n    \"launchDate\": \"1988-07-04T06:28:50.279Z\",\n    \"price\": 79309139.85579339,\n    \"title\": \"Excepteur commodo irure mollit\",\n    \"_links\": {}\n}",
											"options": {
												"raw": {
													"language": "json"
												}
											}
										},
										"url": {
											"raw": "{{baseUrl}}/api/book/v1",
											"host": [
												"{{baseUrl}}"
											],
											"path": [
												"api",
												"book",
												"v1"
											]
										}
									},
									"status": "Internal Server Error",
									"code": 500,
									"_postman_previewlanguage": "json",
									"header": [
										{
											"key": "Content-Type",
											"value": "application/json"
										}
									],
									"cookie": [],
									"body": "{}"
								}
							]
						},
						{
							"name": "Deletes a book",
							"request": {
								"method": "DELETE",
								"header": [
									{
										"key": "Authorization",
										"value": "Bearer {{refreshToken}}",
										"type": "text"
									}
								],
								"url": {
									"raw": "{{baseUrl}}/api/book/v1/:id",
									"host": [
										"{{baseUrl}}"
									],
									"path": [
										"api",
										"book",
										"v1",
										":id"
									],
									"variable": [
										{
											"key": "id",
											"value": "98161935",
											"description": "(Required) "
										}
									]
								},
								"description": "Deletes a book by their Id."
							},
							"response": [
								{
									"name": "No Content",
									"originalRequest": {
										"method": "DELETE",
										"header": [],
										"url": {
											"raw": "{{baseUrl}}/api/book/v1/:id",
											"host": [
												"{{baseUrl}}"
											],
											"path": [
												"api",
												"book",
												"v1",
												":id"
											],
											"variable": [
												{
													"key": "id",
													"value": "98161935",
													"description": "(Required) "
												}
											]
										}
									},
									"status": "No Content",
									"code": 204,
									"_postman_previewlanguage": "json",
									"header": [
										{
											"key": "Content-Type",
											"value": "application/hal+json"
										}
									],
									"cookie": [],
									"body": "{}"
								},
								{
									"name": "Bad Request",
									"originalRequest": {
										"method": "DELETE",
										"header": [],
										"url": {
											"raw": "{{baseUrl}}/api/book/v1/:id",
											"host": [
												"{{baseUrl}}"
											],
											"path": [
												"api",
												"book",
												"v1",
												":id"
											],
											"variable": [
												{
													"key": "id",
													"value": "98161935",
													"description": "(Required) "
												}
											]
										}
									},
									"status": "Bad Request",
									"code": 400,
									"_postman_previewlanguage": "json",
									"header": [
										{
											"key": "Content-Type",
											"value": "application/hal+json"
										}
									],
									"cookie": [],
									"body": "{}"
								},
								{
									"name": "Unauthorized",
									"originalRequest": {
										"method": "DELETE",
										"header": [],
										"url": {
											"raw": "{{baseUrl}}/api/book/v1/:id",
											"host": [
												"{{baseUrl}}"
											],
											"path": [
												"api",
												"book",
												"v1",
												":id"
											],
											"variable": [
												{
													"key": "id",
													"value": "98161935",
													"description": "(Required) "
												}
											]
										}
									},
									"status": "Unauthorized",
									"code": 401,
									"_postman_previewlanguage": "json",
									"header": [
										{
											"key": "Content-Type",
											"value": "application/hal+json"
										}
									],
									"cookie": [],
									"body": "{}"
								},
								{
									"name": "Not Found",
									"originalRequest": {
										"method": "DELETE",
										"header": [],
										"url": {
											"raw": "{{baseUrl}}/api/book/v1/:id",
											"host": [
												"{{baseUrl}}"
											],
											"path": [
												"api",
												"book",
												"v1",
												":id"
											],
											"variable": [
												{
													"key": "id",
													"value": "98161935",
													"description": "(Required) "
												}
											]
										}
									},
									"status": "Not Found",
									"code": 404,
									"_postman_previewlanguage": "json",
									"header": [
										{
											"key": "Content-Type",
											"value": "application/hal+json"
										}
									],
									"cookie": [],
									"body": "{}"
								},
								{
									"name": "Internal error",
									"originalRequest": {
										"method": "DELETE",
										"header": [],
										"url": {
											"raw": "{{baseUrl}}/api/book/v1/:id",
											"host": [
												"{{baseUrl}}"
											],
											"path": [
												"api",
												"book",
												"v1",
												":id"
											],
											"variable": [
												{
													"key": "id",
													"value": "98161935",
													"description": "(Required) "
												}
											]
										}
									},
									"status": "Internal Server Error",
									"code": 500,
									"_postman_previewlanguage": "json",
									"header": [
										{
											"key": "Content-Type",
											"value": "application/hal+json"
										}
									],
									"cookie": [],
									"body": "{}"
								}
							]
						}
					]
				},
				{
					"name": "Login",
					"item": [
						{
							"name": "Authenticate an user",
							"event": [
								{
									"listen": "test",
									"script": {
										"exec": [
											"if (responseCode.code >= 200 && responseCode.code <= 299) {",
											"    var jsonData = JSON.parse(responseBody);",
											"    postman.setEnvironmentVariable('bearer_token', jsonData.accessToken);",
											"    postman.setEnvironmentVariable('refreshToken', jsonData.accessToken);",
											"}"
										],
										"type": "text/javascript"
									}
								}
							],
							"request": {
								"method": "POST",
								"header": [
									{
										"key": "Accept",
										"value": "application/json",
										"disabled": true
									},
									{
										"key": "Content-Type",
										"name": "Content-Type",
										"value": "application/json",
										"type": "text",
										"disabled": true
									}
								],
								"body": {
									"mode": "raw",
									"raw": "{\n\t\"username\":\"{{username}}\",\n\t\"password\":\"{{password}}\"\n}",
									"options": {
										"raw": {
											"language": "json"
										}
									}
								},
								"url": {
									"raw": "{{baseUrl}}/auth/signin",
									"host": [
										"{{baseUrl}}"
									],
									"path": [
										"auth",
										"signin"
									]
								}
							},
							"response": []
						},
						{
							"name": "Refresh token for authenticated user",
							"event": [
								{
									"listen": "test",
									"script": {
										"exec": [
											"if (responseCode.code >= 200 && responseCode.code <= 299) {",
											"    var jsonData = JSON.parse(responseBody);",
											"    postman.setEnvironmentVariable('accessToken', jsonData.accessToken);",
											"    postman.setEnvironmentVariable('refreshToken', jsonData.accessToken);",
											"}"
										],
										"type": "text/javascript"
									}
								}
							],
							"request": {
								"method": "PUT",
								"header": [
									{
										"key": "Accept",
										"value": "application/json"
									},
									{
										"key": "Content-Type",
										"name": "Content-Type",
										"value": "application/json",
										"type": "text"
									},
									{
										"key": "Authorization",
										"value": "Bearer {{refreshToken}}",
										"type": "text"
									}
								],
								"url": {
									"raw": "{{baseUrl}}/auth/refresh/{{username}}",
									"host": [
										"{{baseUrl}}"
									],
									"path": [
										"auth",
										"refresh",
										"{{username}}"
									]
								}
							},
							"response": []
						}
					]
				},
				{
					"name": "File",
					"item": [
						{
							"name": "upload Multiple Files",
							"request": {
								"method": "POST",
								"header": [
									{
										"key": "Accept",
										"value": "application/hal+json"
									},
									{
										"key": "Authorization",
										"value": "Bearer {{refreshToken}}",
										"type": "text"
									}
								],
								"body": {
									"mode": "formdata",
									"formdata": [
										{
											"key": "files",
											"type": "file",
											"src": [
												"/D:/1_dbeTcEaIPgyZZ6aaC519RQ.png",
												"/D:/4y634TJm_400x400.jpg",
												"/D:/Comunicado_Cancelamento_Kiss_Uberlandia.pdf",
												"/D:/junit5-logo.png",
												"/D:/KISS_NOVAS_DATAS.pdf",
												"/D:/logo.svg"
											]
										}
									]
								},
								"url": {
									"raw": "{{baseUrl}}/api/file/v1/uploadMultipleFiles",
									"host": [
										"{{baseUrl}}"
									],
									"path": [
										"api",
										"file",
										"v1",
										"uploadMultipleFiles"
									]
								}
							},
							"response": [
								{
									"name": "OK",
									"originalRequest": {
										"method": "POST",
										"header": [],
										"url": {
											"raw": "{{baseUrl}}/api/file/v1/uploadMultipleFiles?files=ad officia do&files=commodo aute dolor",
											"host": [
												"{{baseUrl}}"
											],
											"path": [
												"api",
												"file",
												"v1",
												"uploadMultipleFiles"
											],
											"query": [
												{
													"key": "files",
													"value": "ad officia do"
												},
												{
													"key": "files",
													"value": "commodo aute dolor"
												}
											]
										}
									},
									"status": "OK",
									"code": 200,
									"_postman_previewlanguage": "json",
									"header": [
										{
											"key": "Content-Type",
											"value": "application/hal+json"
										}
									],
									"cookie": [],
									"body": "[\n  {\n    \"fileName\": \"reprehenderit\",\n    \"fileDownloadUri\": \"dolore ex deserunt dolore\",\n    \"fileType\": \"dolor labore occaecat proident\",\n    \"size\": -77986298\n  },\n  {\n    \"fileName\": \"consectetur anim dolore proident\",\n    \"fileDownloadUri\": \"eiusmod id\",\n    \"fileType\": \"Ut enim reprehenderit ex\",\n    \"size\": 41015727\n  }\n]"
								}
							]
						},
						{
							"name": "upload File",
							"request": {
								"method": "POST",
								"header": [
									{
										"key": "Content-Type",
										"value": "application/json"
									},
									{
										"key": "Accept",
										"value": "application/hal+json",
										"disabled": true
									},
									{
										"key": "Authorization",
										"value": "Bearer {{refreshToken}}",
										"type": "text"
									}
								],
								"body": {
									"mode": "formdata",
									"formdata": [
										{
											"key": "file",
											"type": "file",
											"src": "/D:/1_dbeTcEaIPgyZZ6aaC519RQ.png"
										}
									]
								},
								"url": {
									"raw": "{{baseUrl}}/api/file/v1/uploadFile",
									"host": [
										"{{baseUrl}}"
									],
									"path": [
										"api",
										"file",
										"v1",
										"uploadFile"
									]
								}
							},
							"response": [
								{
									"name": "OK",
									"originalRequest": {
										"method": "POST",
										"header": [],
										"body": {
											"mode": "raw",
											"raw": "{\n  \"file\": \"ea et\"\n}",
											"options": {
												"raw": {
													"language": "json"
												}
											}
										},
										"url": {
											"raw": "{{baseUrl}}/api/file/v1/uploadFile",
											"host": [
												"{{baseUrl}}"
											],
											"path": [
												"api",
												"file",
												"v1",
												"uploadFile"
											]
										}
									},
									"status": "OK",
									"code": 200,
									"_postman_previewlanguage": "json",
									"header": [
										{
											"key": "Content-Type",
											"value": "application/hal+json"
										}
									],
									"cookie": [],
									"body": "{\n  \"fileName\": \"eiusmo\",\n  \"fileDownloadUri\": \"nisi Lorem\",\n  \"fileType\": \"aliqua amet tempor nisi\",\n  \"size\": 76592894\n}"
								}
							]
						},
						{
							"name": "download File",
							"request": {
								"method": "GET",
								"header": [
									{
										"key": "Accept",
										"value": "application/hal+json"
									},
									{
										"key": "Authorization",
										"value": "Bearer {{refreshToken}}",
										"type": "text"
									}
								],
								"url": {
									"raw": "{{baseUrl}}/api/file/v1/downloadFile/1_dbeTcEaIPgyZZ6aaC519RQ.png",
									"host": [
										"{{baseUrl}}"
									],
									"path": [
										"api",
										"file",
										"v1",
										"downloadFile",
										"1_dbeTcEaIPgyZZ6aaC519RQ.png"
									]
								}
							},
							"response": [
								{
									"name": "OK",
									"originalRequest": {
										"method": "GET",
										"header": [],
										"url": {
											"raw": "{{baseUrl}}/api/file/v1/downloadFile/:fileName",
											"host": [
												"{{baseUrl}}"
											],
											"path": [
												"api",
												"file",
												"v1",
												"downloadFile",
												":fileName"
											],
											"variable": [
												{
													"key": "fileName",
													"value": "id",
													"description": "(Required) "
												}
											]
										}
									},
									"status": "OK",
									"code": 200,
									"_postman_previewlanguage": "json",
									"header": [
										{
											"key": "Content-Type",
											"value": "application/hal+json"
										}
									],
									"cookie": [],
									"body": "\"id\""
								}
							]
						}
					]
				}
			]
		}
	],
	"variable": [
		{
			"key": "baseUrl",
			"value": "http://localhost:8080",
			"type": "string"
		}
	]
}